CramersVFunction/__init__.py
cramersv-0.0.1.dist-info/LICENCE.txt
cramersv-0.0.1.dist-info/METADATA
cramersv-0.0.1.dist-info/WHEEL
cramersv-0.0.1.dist-info/top_level.txt
cramersv-0.0.1.dist-info/RECORD
