Metadata-Version: 2.1
Name: cramersv
Version: 0.0.1
Summary: A package to calculate the CramersV correlation coefficient for categorical data
Home-page: https://github.com/arvind444/CramersV_correlation
Author: Arvindkumar
Author-email: arvindkumar1998ece@gmail.com
License: MIT
Keywords: to findcategorical to categorical data correlation
Platform: UNKNOWN
Classifier: Programming Language :: Python :: 3
Classifier: License :: OSI Approved :: MIT License
Classifier: Operating System :: OS Independent
Requires-Python: >=3.6
License-File: LICENCE.txt
Requires-Dist: pandas
Requires-Dist: numpy
Requires-Dist: scipy
